amtui/__init__.py
amtui/cli.py
amtui/custom_status_bar.py
amtui/images.py
amtui/main.py
amtui-0.1.2.dist-info/AUTHORS.rst
amtui-0.1.2.dist-info/LICENSE
amtui-0.1.2.dist-info/METADATA
amtui-0.1.2.dist-info/WHEEL
amtui-0.1.2.dist-info/entry_points.txt
amtui-0.1.2.dist-info/top_level.txt
amtui-0.1.2.dist-info/RECORD
