Metadata-Version: 2.1
Name: amtui
Version: 0.1.2
Summary: A user interface to the Artifact Management Tool
Home-page: https://github.com/bellockk/amtui
Author: Kenneth E. Bellock
Author-email: ken@bellock.net
License: MIT license
Keywords: amtui
Platform: UNKNOWN
Classifier: Development Status :: 2 - Pre-Alpha
Classifier: Intended Audience :: Developers
Classifier: License :: OSI Approved :: MIT License
Classifier: Natural Language :: English
Classifier: Programming Language :: Python :: 3.6
Classifier: Programming Language :: Python :: 3.7
Requires-Dist: Click (>=6.0)
Requires-Dist: amtool (>=0.1.9)
Requires-Dist: wxPython (>=4.0.6)
